<?xml version='1.0' encoding='UTF-8'?>
<multistatus xmlns='DAV:'>
  <response>
    <href>$addressbookpath1:/45aad6d69d91e1e6e37c9fd1d38b950d.vcf</href>
    <propstat>
      <prop>
        <getetag>"c9c80708eda258e871b3e6f02e6383d8"</getetag>
        <address-data xmlns='urn:ietf:params:xml:ns:carddav'><![CDATA[BEGIN:VCARD
VERSION:3.0
PRODID:-//CALENDARSERVER.ORG//NONSGML Version 1//EN
UID:78b64b6b-80b9-4b8a-bd81-8f36645d8bbf
FN:user02
N:user02;;;;
X-ADDRESSBOOKSERVER-KIND:group
X-ADDRESSBOOKSERVER-MEMBER:urn:uuid:3765A955-1B96-41EA-994D-335192BEDCCD
X-ADDRESSBOOKSERVER-MEMBER:urn:uuid:44745975-AE6D-4FB0-80A6-A298427E047A
X-ADDRESSBOOKSERVER-MEMBER:urn:uuid:934731C6-1C95-4C40-BE1F-FA4215B2307B
X-ADDRESSBOOKSERVER-MEMBER:urn:uuid:ED7A5AEC-AB19-4CE0-AD6A-2923A3E5C4E1
X-ADDRESSBOOKSERVER-MEMBER:urn:uuid:FCBA0FA3-00B2-4C95-B4EC-4CCC4843F8B1
X-ADDRESSBOOKSERVER-MEMBER:urn:uuid:user01-uid01
X-ADDRESSBOOKSERVER-MEMBER:urn:uuid:user01-uid02
END:VCARD
]]></address-data>
      </prop>
      <status>HTTP/1.1 200 OK</status>
    </propstat>
  </response>
</multistatus>
